azureml/__init__.py
azureml/datadrift/__init__.py
azureml/datadrift/_datadiff.py
azureml/datadrift/_generate_script_databricks_init_dev.py
azureml/datadrift/_generate_script_databricks_init_prod.py
azureml/datadrift/_model_serving_dataset.py
azureml/datadrift/_result_handler.py
azureml/datadrift/_schedule_state.py
azureml/datadrift/alert_configuration.py
azureml/datadrift/datadriftdetector.py
azureml/datadrift/_logging/__init__.py
azureml/datadrift/_logging/_telemetry_logger.py
azureml/datadrift/_logging/_telemetry_logger_context_adapter.py
azureml/datadrift/_logging/_telemetry_logger_context_filter.py
azureml/datadrift/_logging/_telemetry_logger_context_formatter.py
azureml/datadrift/_restclient/__init__.py
azureml/datadrift/_restclient/api_versions.py
azureml/datadrift/_restclient/datadrift_client.py
azureml/datadrift/_restclient/modelserving_client.py
azureml/datadrift/_restclient/rest_client.py
azureml/datadrift/_restclient/version.py
azureml/datadrift/_restclient/models/__init__.py
azureml/datadrift/_restclient/models/alert_configuration.py
azureml/datadrift/_restclient/models/alert_configuration_py3.py
azureml/datadrift/_restclient/models/create_data_drift_dto.py
azureml/datadrift/_restclient/models/create_data_drift_dto_py3.py
azureml/datadrift/_restclient/models/create_data_drift_run_dto.py
azureml/datadrift/_restclient/models/create_data_drift_run_dto_py3.py
azureml/datadrift/_restclient/models/data_drift_dto.py
azureml/datadrift/_restclient/models/data_drift_dto_py3.py
azureml/datadrift/_restclient/models/data_drift_metric_dto.py
azureml/datadrift/_restclient/models/data_drift_metric_dto_py3.py
azureml/datadrift/_restclient/models/data_drift_query_dto.py
azureml/datadrift/_restclient/models/data_drift_query_dto_py3.py
azureml/datadrift/_restclient/models/data_drift_run_dto.py
azureml/datadrift/_restclient/models/data_drift_run_dto_py3.py
azureml/datadrift/_restclient/models/data_drift_run_result_dto.py
azureml_datadrift-1.60.0.dist-info/licenses/LICENSE.txt
azureml_datadrift-1.60.0.dist-info/METADATA
azureml_datadrift-1.60.0.dist-info/WHEEL
azureml_datadrift-1.60.0.dist-info/top_level.txt
azureml_datadrift-1.60.0.dist-info/RECORD
