Metadata-Version: 2.4
Name: azureml-datadrift
Version: 1.60.0
Summary: Contains functionality for data drift detection for     various datasets used in machine learning.
Home-page: https://docs.microsoft.com/python/api/overview/azure/ml/?view=azure-ml-py
Author: Microsoft Corp
License: https://aka.ms/azureml-sdk-license
Requires-Python: >=3.7,<4
License-File: LICENSE.txt
Requires-Dist: azureml-core~=1.60.0
Requires-Dist: azureml-dataset-runtime[fuse,pandas]~=1.60.0
Requires-Dist: azureml-telemetry~=1.60.0
Requires-Dist: azureml-pipeline-core~=1.60.0
Requires-Dist: msrest>=0.5.1
Requires-Dist: numpy
Requires-Dist: pandas
Requires-Dist: scipy>=1.0.0
Requires-Dist: scikit-learn
Requires-Dist: lightgbm
Requires-Dist: jsonpickle
Requires-Dist: pyspark
Requires-Dist: matplotlib<=3.6.3,>=3.0.2
Provides-Extra: databricks
Requires-Dist: pyOpenSSL==16.0.0; extra == "databricks"
Requires-Dist: cryptography==1.5; extra == "databricks"
Requires-Dist: ipython==2.2.0; extra == "databricks"
Requires-Dist: numpy<=1.16.2,>=1.11.0; extra == "databricks"
Requires-Dist: pandas<=0.23.4,>=0.21.0; extra == "databricks"
Requires-Dist: scipy<=1.1.0,>=1.0.0; extra == "databricks"
Requires-Dist: tornado==5.1.1; extra == "databricks"
Dynamic: author
Dynamic: description
Dynamic: description-content-type
Dynamic: home-page
Dynamic: license
Dynamic: license-file
Dynamic: provides-extra
Dynamic: requires-dist
Dynamic: requires-python
Dynamic: summary
